{"per_page":10,"total":3,"current":1,"data":[{"title":"字节面试-PHP","date":"2021-03-04T21:04:08.000Z","author":"Vale Sail","excerpt":"","slug":"字节面试"},{"title":"golang流水线","date":"2020-06-07T15:32:15.000Z","author":"Vale Sail","excerpt":"","slug":"golang流水线"},{"title":"golang界面程序","date":"2020-06-01T18:11:16.000Z","author":"Vale Sail","excerpt":"","slug":"golang界面程序"},{"title":"0521面试下","date":"2020-05-24T21:15:05.000Z","author":"Vale Sail","excerpt":"","slug":"0521面试下"},{"title":"0522坑","date":"2020-05-24T20:40:00.000Z","author":"Vale Sail","excerpt":"","slug":"0522坑"},{"title":"0519面试上","date":"2020-05-19T22:13:00.000Z","author":"Vale Sail","excerpt":"","slug":"0519面试","tags":["计算机网络"],"categories":["面试总结"]},{"title":"0518算法","date":"2020-05-18T23:29:00.000Z","author":"Vale Sail","excerpt":"","slug":"0518","tags":["算法"]},{"title":"0515小记","date":"2020-05-16T13:14:59.000Z","author":"Vale Sail","excerpt":"","slug":"0515小记"},{"title":"0514 小记","date":"2020-05-13T22:51:00.000Z","author":"Vale Sail","excerpt":"","slug":"0514面试总结","categories":["小记"]},{"title":"Redis","date":"2020-05-10T17:13:00.000Z","author":"Vale Sail","excerpt":"","slug":"Redis","tags":["Redis"],"categories":["学习笔记"]}]}